LICENSE.md
setup.py
audiobooker/__init__.py
audiobooker/exceptions.py
audiobooker.egg-info/PKG-INFO
audiobooker.egg-info/SOURCES.txt
audiobooker.egg-info/dependency_links.txt
audiobooker.egg-info/requires.txt
audiobooker.egg-info/top_level.txt
audiobooker/scrappers/__init__.py
audiobooker/scrappers/audioanarchy.py
audiobooker/scrappers/goldenaudiobooks.py
audiobooker/scrappers/librivox.py
audiobooker/scrappers/loyalbooks.py
audiobooker/scrappers/stephenkingaudiobooks.py
audiobooker/scrappers/storynory.py
audiobooker/scrappers/thoughtaudio.py
audiobooker/utils/__init__.py
audiobooker/utils/google_search.py