Metadata-Version: 2.1
Name: audiobooker
Version: 0.3.1
Summary: audio book scrapper
Home-page: https://github.com/OpenJarbas/audiobooker
Author: jarbasAI
Author-email: jarbasai@mailfence.com
License: MIT
Platform: UNKNOWN
License-File: LICENSE.md
